NeuroKit_Eda_Analaysis/__init__.py
NeuroKit_Eda_Analaysis/data_processing.py
NeuroKit_Eda_Analaysis/metrics.py
NeuroKit_Eda_Analaysis/plotting.py
NeuroKit_Eda_Analaysis/signal_processing.py
NeuroKit_Eda_Analaysis-0.1.dist-info/License.txt
NeuroKit_Eda_Analaysis-0.1.dist-info/METADATA
NeuroKit_Eda_Analaysis-0.1.dist-info/WHEEL
NeuroKit_Eda_Analaysis-0.1.dist-info/top_level.txt
NeuroKit_Eda_Analaysis-0.1.dist-info/RECORD
